memery/__init__.py
memery/cli.py
memery/core.py
memery/crafter.py
memery/encoder.py
memery/gui.py
memery/indexer.py
memery/loader.py
memery/ranker.py
memery/streamlit_app.py
memery-0.15.0.dist-info/entry_points.txt
memery-0.15.0.dist-info/LICENSE
memery-0.15.0.dist-info/WHEEL
memery-0.15.0.dist-info/METADATA
memery-0.15.0.dist-info/RECORD
